[
    {
        "estimator": "RandomForestClassifier",
        "mean": 0.4976768968456947,
        "standard_deviation": 0.05385847340805419,
        "median": 0.4926470588235294,
        "variance": 0.0029007351578460806,
        "standard_error": 0.017031544726906246,
        "min_max_score": [
            0.4265,
            0.5797
        ],
        "estimator_params": {
            "bootstrap": true,
            "ccp_alpha": 0.0,
            "class_weight": null,
            "criterion": "log_loss",
            "max_depth": 27,
            "max_features": "sqrt",
            "max_leaf_nodes": null,
            "max_samples": null,
            "min_impurity_decrease": 0.0,
            "min_samples_leaf": 25,
            "min_samples_split": 6,
            "min_weight_fraction_leaf": 0.0,
            "monotonic_cst": null,
            "n_estimators": 60,
            "n_jobs": null,
            "oob_score": false,
            "random_state": null,
            "verbose": 0,
            "warm_start": false
        },
        "scoring": "accuracy",
        "features": "idade,  peso,  duracao_sessao,  nivel_experiencia,  percentual_gordura",
        "pre_processing_time": "00:00:00.000",
        "feature_selection_time": "00:00:01.000",
        "search_time": "00:00:11.000",
        "validation_time": "00:02:18.000"
    },
    {
        "estimator": "RandomForestClassifier",
        "mean": 0.4976768968456947,
        "standard_deviation": 0.05385847340805419,
        "median": 0.4926470588235294,
        "variance": 0.0029007351578460806,
        "standard_error": 0.017031544726906246,
        "min_max_score": [
            0.4265,
            0.5797
        ],
        "estimator_params": {
            "bootstrap": true,
            "ccp_alpha": 0.0,
            "class_weight": null,
            "criterion": "log_loss",
            "max_depth": 27,
            "max_features": "sqrt",
            "max_leaf_nodes": null,
            "max_samples": null,
            "min_impurity_decrease": 0.0,
            "min_samples_leaf": 25,
            "min_samples_split": 6,
            "min_weight_fraction_leaf": 0.0,
            "monotonic_cst": null,
            "n_estimators": 60,
            "n_jobs": null,
            "oob_score": false,
            "random_state": null,
            "verbose": 0,
            "warm_start": false
        },
        "scoring": "accuracy",
        "features": "idade,  peso,  duracao_sessao,  nivel_experiencia,  percentual_gordura",
        "pre_processing_time": "00:00:01.000",
        "feature_selection_time": "00:00:01.000",
        "search_time": "00:00:01.000",
        "validation_time": "00:00:01.000"
    },
    {
        "estimator": "RandomForestClassifier",
        "mean": 0.4976768968456947,
        "standard_deviation": 0.05385847340805419,
        "median": 0.4926470588235294,
        "variance": 0.0029007351578460806,
        "standard_error": 0.017031544726906246,
        "min_max_score": [
            0.4265,
            0.5797
        ],
        "estimator_params": {
            "bootstrap": true,
            "ccp_alpha": 0.0,
            "class_weight": null,
            "criterion": "log_loss",
            "max_depth": 27,
            "max_features": "sqrt",
            "max_leaf_nodes": null,
            "max_samples": null,
            "min_impurity_decrease": 0.0,
            "min_samples_leaf": 25,
            "min_samples_split": 6,
            "min_weight_fraction_leaf": 0.0,
            "monotonic_cst": null,
            "n_estimators": 60,
            "n_jobs": null,
            "oob_score": false,
            "random_state": null,
            "verbose": 0,
            "warm_start": false
        },
        "scoring": "accuracy",
        "features": "idade,  peso,  duracao_sessao,  nivel_experiencia,  percentual_gordura",
        "pre_processing_time": "00:00:01.000",
        "feature_selection_time": "00:00:01.000",
        "search_time": "00:00:01.000",
        "validation_time": "00:00:01.000"
    },
    {
        "estimator": "KNeighborsClassifier",
        "mean": 0.5037297527706734,
        "standard_deviation": 0.04974565631786195,
        "median": 0.49264705882352944,
        "variance": 0.002474630322494839,
        "standard_error": 0.015730957766438885,
        "min_max_score": [
            0.4412,
            0.6176
        ],
        "estimator_params": {
            "algorithm": "brute",
            "leaf_size": 30,
            "metric": "minkowski",
            "metric_params": null,
            "n_jobs": null,
            "n_neighbors": 6,
            "p": 2,
            "weights": "distance"
        },
        "scoring": "accuracy",
        "features": "altura,  duracao_sessao,  tipo_treino,  nivel_experiencia,  percentual_gordura",
        "pre_processing_time": "00:00:00.000",
        "feature_selection_time": "00:00:00.000",
        "search_time": "00:00:05.000",
        "validation_time": "00:01:18.000"
    },
    {
        "estimator": "KNeighborsClassifier",
        "mean": 0.4934143222506394,
        "standard_deviation": 0.05793068230527845,
        "median": 0.4817774936061381,
        "variance": 0.003355963952355102,
        "standard_error": 0.01831929024922937,
        "min_max_score": [
            0.4265,
            0.6176
        ],
        "estimator_params": {
            "algorithm": "brute",
            "leaf_size": 30,
            "metric": "minkowski",
            "metric_params": null,
            "n_jobs": null,
            "n_neighbors": 19,
            "p": 2,
            "weights": "distance"
        },
        "scoring": "accuracy",
        "features": "altura,  duracao_sessao,  tipo_treino,  nivel_experiencia,  percentual_gordura",
        "pre_processing_time": "00:00:00.000",
        "feature_selection_time": "00:00:00.000",
        "search_time": "00:00:08.000",
        "validation_time": "00:02:34.000"
    }
]